azure_monitor/__init__.py
azure_monitor/options.py
azure_monitor/protocol.py
azure_monitor/storage.py
azure_monitor/utils.py
azure_monitor/version.py
azure_monitor/export/__init__.py
azure_monitor/export/metrics/__init__.py
azure_monitor/export/trace/__init__.py
azure_monitor/sdk/__init__.py
azure_monitor/sdk/auto_collection/__init__.py
azure_monitor/sdk/auto_collection/dependency_metrics.py
azure_monitor/sdk/auto_collection/metrics_span_processor.py
azure_monitor/sdk/auto_collection/performance_metrics.py
azure_monitor/sdk/auto_collection/request_metrics.py
azure_monitor/sdk/auto_collection/utils.py
azure_monitor/sdk/auto_collection/live_metrics/__init__.py
azure_monitor/sdk/auto_collection/live_metrics/exporter.py
azure_monitor/sdk/auto_collection/live_metrics/manager.py
azure_monitor/sdk/auto_collection/live_metrics/sender.py
azure_monitor/sdk/auto_collection/live_metrics/utils.py
opentelemetry_azure_monitor-0.6b1.dist-info/METADATA
opentelemetry_azure_monitor-0.6b1.dist-info/WHEEL
opentelemetry_azure_monitor-0.6b1.dist-info/top_level.txt
opentelemetry_azure_monitor-0.6b1.dist-info/RECORD
